gaecl/__init__.py
gaecl/logger.py
gaecl-0.1.0.dist-info/LICENSE.txt
gaecl-0.1.0.dist-info/METADATA
gaecl-0.1.0.dist-info/WHEEL
gaecl-0.1.0.dist-info/top_level.txt
gaecl-0.1.0.dist-info/RECORD
